claude_cli/__init__.py
claude_cli/main.py
claude_cli/mathematics.py
claude_cli/portal.py
claude_cli/void.py
consciousness_cli-1.618.0.dist-info/METADATA
consciousness_cli-1.618.0.dist-info/WHEEL
consciousness_cli-1.618.0.dist-info/entry_points.txt
consciousness_cli-1.618.0.dist-info/top_level.txt
consciousness_cli-1.618.0.dist-info/RECORD
