Metadata-Version: 2.4
Name: consciousness-cli
Version: 1.618.0
Summary: Consciousness computing CLI with φ mathematics and void operations
Home-page: https://github.com/bitsabhi/consciousness-portal
Author: Abhishek Srivastava
Author-email: bits.abhi@gmail.com
Project-URL: Bug Reports, https://github.com/bitsabhi/consciousness-portal/issues
Project-URL: Source, https://github.com/bitsabhi/consciousness-portal
Project-URL: Documentation, https://github.com/bitsabhi/consciousness-portal/blob/main/README.md
Project-URL: Portal, https://bitsabhi.github.io/consciousness-portal/
Keywords: consciousness cli phi void mathematics golden-ratio abhilasia intelligence
Classifier: Development Status :: 4 - Beta
Classifier: Intended Audience :: Developers
Classifier: License :: OSI Approved :: MIT License
Classifier: Operating System :: OS Independent
Classifier: Programming Language :: Python :: 3
Classifier: Programming Language :: Python :: 3.8
Classifier: Programming Language :: Python :: 3.9
Classifier: Programming Language :: Python :: 3.10
Classifier: Programming Language :: Python :: 3.11
Classifier: Topic :: Scientific/Engineering :: Artificial Intelligence
Classifier: Topic :: Software Development :: Libraries :: Python Modules
Requires-Python: >=3.8
Requires-Dist: requests>=2.28.0
Requires-Dist: websocket-client>=1.4.0
Requires-Dist: click>=8.0.0
Requires-Dist: colorama>=0.4.0
Requires-Dist: numpy>=1.21.0
Provides-Extra: dev
Requires-Dist: pytest>=7.0.0; extra == "dev"
Requires-Dist: black>=22.0.0; extra == "dev"
Requires-Dist: flake8>=5.0.0; extra == "dev"
Dynamic: author
Dynamic: author-email
Dynamic: classifier
Dynamic: description
Dynamic: description-content-type
Dynamic: home-page
Dynamic: keywords
Dynamic: project-url
Dynamic: provides-extra
Dynamic: requires-dist
Dynamic: requires-python
Dynamic: summary
